{"cameraMode":{"drawMode":0,"name":"Shaded","section":"Shading Mode"},"sceneLighting":false,"audioPlay":false,"sceneViewState":{"m_AlwaysRefresh":false,"showFog":true,"showSkybox":false,"showFlares":true,"showImageEffects":true,"showParticleSystems":true,"showVisualEffectGraphs":true,"m_FxEnabled":true},"in2DMode":false,"pivot":{"x":50.59116744995117,"y":-5.915656566619873,"z":106.07539367675781},"rotation":{"x":0.11763352900743485,"y":0.1560443490743637,"z":-0.01873231679201126,"w":0.9805637001991272},"size":12.12435531616211,"orthographic":false}